{
  "schema_version": "fact_anchor.v1",
  "topic_id": "radar_level_gauge_fmcw_pulse_distance_level_dielectric_constant_false_echo_installation_error",
  "title_ko": "레이더식 레벨계의 FMCW·펄스 방식, 거리·레벨 측정원리, 유전율 영향 및 허위에코·설치오차",
  "question_type_hint": "PRINCIPLE_INTERPRETATION",
  "anchors": [
    {
      "id": "radar_level_system_structure",
      "anchor_id": "radar_level_system_structure",
      "statement": "레이더식 레벨계는 송신·주파수생성부, 안테나, 수신·혼합부, 거리신호처리부, 레벨환산부 및 출력부로 구성되며 펄스식과 FMCW식 모두 표면 반사에코를 이용한다.",
      "importance": "core",
      "keywords": [
        "송신부",
        "안테나",
        "수신부",
        "혼합부",
        "거리신호처리",
        "레벨환산"
      ],
      "core_terms": [
        "송신부",
        "안테나",
        "수신부",
        "혼합부",
        "거리신호처리",
        "레벨환산"
      ],
      "accepted_explanations": [
        "송신에서 반사에코 검출과 레벨 출력까지의 측정사슬을 설명한다.",
        "펄스식과 FMCW식의 공통 구성과 거리추정 방식의 차이를 구분한다."
      ],
      "rejected_explanations": [
        "레이더 센서를 안테나 하나로만 설명한다.",
        "펄스식과 FMCW식을 동일한 시간계측 방식으로 설명한다."
      ],
      "grading_notes": "구성요소를 나열하는 데 그치지 않고 각 요소가 거리와 레벨 계산에 어떻게 연결되는지 평가한다.",
      "source_basis": "Emerson Rosemount and Siemens SITRANS radar manuals.",
      "claim": "레이더식 레벨계는 송신·주파수생성부, 안테나, 수신·혼합부, 거리신호처리부, 레벨환산부 및 출력부로 구성되며 펄스식과 FMCW식 모두 표면 반사에코를 이용한다.",
      "description": "레이더식 레벨계는 송신·주파수생성부, 안테나, 수신·혼합부, 거리신호처리부, 레벨환산부 및 출력부로 구성되며 펄스식과 FMCW식 모두 표면 반사에코를 이용한다."
    },
    {
      "id": "radar_electromagnetic_wave_reflection",
      "anchor_id": "radar_electromagnetic_wave_reflection",
      "statement": "안테나는 마이크로파 전자기파를 방사하고 액면 또는 분체표면에서 반사된 에코를 수신하며 레이더식 레벨계는 음파가 아니라 전자기파를 사용한다.",
      "importance": "core",
      "keywords": [
        "전자기파",
        "마이크로파",
        "안테나",
        "반사에코",
        "액면",
        "분체표면"
      ],
      "core_terms": [
        "전자기파",
        "마이크로파",
        "안테나",
        "반사에코",
        "액면",
        "분체표면"
      ],
      "accepted_explanations": [
        "기체공간에서 전자기파가 표면까지 전파된 후 반사되는 원리를 설명한다.",
        "초음파식의 음파전파와 구분한다."
      ],
      "rejected_explanations": [
        "공기 중 음속으로 전파시간을 계산한다.",
        "레이더가 매질 내부의 기계적 진동을 측정한다고 설명한다."
      ],
      "grading_notes": "레이더와 초음파의 전파원리를 혼동하면 중대한 오류로 평가한다.",
      "source_basis": "Emerson, Siemens, VEGA and Endress+Hauser industrial radar guidance.",
      "claim": "안테나는 마이크로파 전자기파를 방사하고 액면 또는 분체표면에서 반사된 에코를 수신하며 레이더식 레벨계는 음파가 아니라 전자기파를 사용한다.",
      "description": "안테나는 마이크로파 전자기파를 방사하고 액면 또는 분체표면에서 반사된 에코를 수신하며 레이더식 레벨계는 음파가 아니라 전자기파를 사용한다."
    },
    {
      "id": "radar_pulse_time_of_flight",
      "anchor_id": "radar_pulse_time_of_flight",
      "statement": "펄스식 레이더는 송신펄스와 반사펄스 사이의 왕복 비행시간 τ를 측정하며 수신지연은 안테나와 표면 사이 왕복경로에 해당한다.",
      "importance": "core",
      "keywords": [
        "펄스 레이더",
        "비행시간",
        "왕복시간",
        "송신펄스",
        "반사펄스",
        "수신지연"
      ],
      "core_terms": [
        "펄스 레이더",
        "비행시간",
        "왕복시간",
        "송신펄스",
        "반사펄스",
        "수신지연"
      ],
      "accepted_explanations": [
        "송신시각과 에코 수신시각의 차이를 왕복시간으로 설명한다.",
        "왕복시간을 편도거리로 변환해야 함을 설명한다."
      ],
      "rejected_explanations": [
        "수신지연을 표면의 이동속도로 해석한다.",
        "왕복과 편도 개념을 구분하지 않는다."
      ],
      "grading_notes": "펄스식의 직접 측정량은 에코의 왕복 지연시간이다.",
      "source_basis": "Emerson FMCW Technology, Siemens SITRANS manuals and Texas Instruments FMCW radar fundamentals.",
      "claim": "펄스식 레이더는 송신펄스와 반사펄스 사이의 왕복 비행시간 τ를 측정하며 수신지연은 안테나와 표면 사이 왕복경로에 해당한다.",
      "description": "펄스식 레이더는 송신펄스와 반사펄스 사이의 왕복 비행시간 τ를 측정하며 수신지연은 안테나와 표면 사이 왕복경로에 해당한다."
    },
    {
      "id": "radar_pulse_distance_equation",
      "anchor_id": "radar_pulse_distance_equation",
      "statement": "펄스식 자유공간 레이더에서 기준점부터 표면까지의 편도거리는 D=v_g·τ/2로 계산한다. v_g는 실제 전파경로인 기체공간의 전파속도이며 일반 공기에서는 c_0에 가깝다. 고압가스나 고밀도 증기에서는 전파속도 보정 가능성을 검토한다.",
      "importance": "core",
      "keywords": [
        "D=cτ/2",
        "광속",
        "전파속도",
        "왕복경로",
        "편도거리"
      ],
      "core_terms": [
        "D=cτ/2",
        "광속",
        "전파속도",
        "왕복경로",
        "편도거리"
      ],
      "accepted_explanations": [
        "거리식의 각 변수와 2로 나누는 이유를 설명한다.",
        "기체공간에서 전파속도가 대체로 광속에 가까움을 설명한다.",
        "펄스식 자유공간 레이더에서 기준점부터 표면까지의 편도거리는 D=v_g·τ/2로 계산한다. v_g는 실제 전파경로인 기체공간의 전파속도이며 일반 공기에서는 c_0에 가깝다. 고압가스나 고밀도 증기에서는 전파속도 보정 가능성을 검토한다."
      ],
      "rejected_explanations": [
        "D=cτ로 계산한다.",
        "c를 공기 중 음속으로 정의한다.",
        "제품 액체의 유전율을 자유공간 레이더의 기체공간 거리식 전체에 적용한다."
      ],
      "grading_notes": "거리식과 왕복계수 1/2의 의미를 정확히 평가한다. 왕복계수와 실제 전파경로의 유전율을 구분한다.",
      "source_basis": "Emerson FMCW Technology, Siemens SITRANS manuals and Texas Instruments FMCW radar fundamentals.",
      "claim": "펄스식 자유공간 레이더에서 기준점부터 표면까지의 편도거리는 D=v_g·τ/2로 계산한다. v_g는 실제 전파경로인 기체공간의 전파속도이며 일반 공기에서는 c_0에 가깝다. 고압가스나 고밀도 증기에서는 전파속도 보정 가능성을 검토한다.",
      "description": "펄스식 자유공간 레이더에서 기준점부터 표면까지의 편도거리는 D=v_g·τ/2로 계산한다. v_g는 실제 전파경로인 기체공간의 전파속도이며 일반 공기에서는 c_0에 가깝다. 고압가스나 고밀도 증기에서는 전파속도 보정 가능성을 검토한다."
    },
    {
      "id": "radar_fmcw_linear_frequency_sweep",
      "anchor_id": "radar_fmcw_linear_frequency_sweep",
      "statement": "FMCW 레이더는 시간에 따라 주파수가 선형적으로 변하는 처프를 연속 송신하며 스윕 기울기는 S=Δf/T_s로 정의할 수 있다.",
      "importance": "core",
      "keywords": [
        "FMCW",
        "선형 주파수 스윕",
        "처프",
        "연속파",
        "S=Δf/T_s",
        "스윕 기울기"
      ],
      "core_terms": [
        "FMCW",
        "선형 주파수 스윕",
        "처프",
        "연속파",
        "S=Δf/T_s",
        "스윕 기울기"
      ],
      "accepted_explanations": [
        "송신주파수가 스윕시간 동안 연속적으로 변화함을 설명한다.",
        "대역폭과 스윕시간으로 기울기를 정의한다."
      ],
      "rejected_explanations": [
        "FMCW가 단일 고정주파수만 송신한다고 설명한다.",
        "FMCW를 펄스 송수신시각 검출만으로 설명한다."
      ],
      "grading_notes": "FMCW의 핵심은 주파수 변조와 지연수신파의 주파수차이다.",
      "source_basis": "Emerson FMCW Technology, Siemens SITRANS manuals and Texas Instruments FMCW radar fundamentals.",
      "claim": "FMCW 레이더는 시간에 따라 주파수가 선형적으로 변하는 처프를 연속 송신하며 스윕 기울기는 S=Δf/T_s로 정의할 수 있다.",
      "description": "FMCW 레이더는 시간에 따라 주파수가 선형적으로 변하는 처프를 연속 송신하며 스윕 기울기는 S=Δf/T_s로 정의할 수 있다."
    },
    {
      "id": "radar_fmcw_beat_frequency_distance",
      "anchor_id": "radar_fmcw_beat_frequency_distance",
      "statement": "정지표면과 이상적인 선형 처프에서 스윕 기울기 S=B/T_s, 비트주파수 f_b=Sτ이며 거리는 D=v_g·f_b/(2S)=v_g·f_b·T_s/(2B)이다. 실제 계기는 스윕 비선형, 신호처리와 기체공간 전파속도 영향을 함께 고려한다.",
      "importance": "core",
      "keywords": [
        "비트주파수",
        "혼합",
        "f_b=Sτ",
        "D=cf_b/(2S)",
        "지연시간",
        "스윕 기울기"
      ],
      "core_terms": [
        "비트주파수",
        "혼합",
        "f_b=Sτ",
        "D=cf_b/(2S)",
        "지연시간",
        "스윕 기울기"
      ],
      "accepted_explanations": [
        "송신파와 지연수신파의 순간 주파수차가 비트주파수임을 설명한다.",
        "비트주파수와 스윕 기울기를 함께 사용해 거리를 계산한다.",
        "정지표면과 이상적인 선형 처프에서 스윕 기울기 S=B/T_s, 비트주파수 f_b=Sτ이며 거리는 D=v_g·f_b/(2S)=v_g·f_b·T_s/(2B)이다. 실제 계기는 스윕 비선형, 신호처리와 기체공간 전파속도 영향을 함께 고려한다."
      ],
      "rejected_explanations": [
        "비트주파수만으로 스윕조건과 무관하게 거리를 계산한다.",
        "비트주파수를 에코 진폭으로 설명한다.",
        "비트주파수만으로 스윕 기울기와 무관하게 거리를 계산한다."
      ],
      "grading_notes": "정지표적과 이상적 선형 스윕 조건을 전제로 식을 적용한다. 스윕 기울기, 비트주파수와 전파속도를 평가한다.",
      "source_basis": "Emerson FMCW Technology, Siemens SITRANS manuals and Texas Instruments FMCW radar fundamentals.",
      "claim": "정지표면과 이상적인 선형 처프에서 스윕 기울기 S=B/T_s, 비트주파수 f_b=Sτ이며 거리는 D=v_g·f_b/(2S)=v_g·f_b·T_s/(2B)이다. 실제 계기는 스윕 비선형, 신호처리와 기체공간 전파속도 영향을 함께 고려한다.",
      "description": "정지표면과 이상적인 선형 처프에서 스윕 기울기 S=B/T_s, 비트주파수 f_b=Sτ이며 거리는 D=v_g·f_b/(2S)=v_g·f_b·T_s/(2B)이다. 실제 계기는 스윕 비선형, 신호처리와 기체공간 전파속도 영향을 함께 고려한다."
    },
    {
      "id": "radar_bandwidth_range_resolution",
      "anchor_id": "radar_bandwidth_range_resolution",
      "statement": "FMCW의 이상적 거리 분해능은 ΔR≈v_g/(2B)이다. 이는 두 인접 반사면을 분리하는 능력이며 단일 표면의 측정 정확도, 반복성 또는 FFT bin 간격과 동일하지 않다. 정확도는 S/N비, 주파수·위상 추정, 보간, 스윕 선형성, 교정과 설치조건의 영향을 함께 받는다.",
      "importance": "core",
      "keywords": [
        "변조 대역폭",
        "거리 분해능",
        "ΔR≈c/(2B)",
        "인접 반사면",
        "대역폭"
      ],
      "core_terms": [
        "변조 대역폭",
        "거리 분해능",
        "ΔR≈c/(2B)",
        "인접 반사면",
        "대역폭"
      ],
      "accepted_explanations": [
        "대역폭 증가가 거리 분해능을 향상시키는 이유를 설명한다.",
        "분해능과 최대거리·신호대잡음비의 절충을 언급한다.",
        "FMCW의 이상적 거리 분해능은 ΔR≈v_g/(2B)이다. 이는 두 인접 반사면을 분리하는 능력이며 단일 표면의 측정 정확도, 반복성 또는 FFT bin 간격과 동일하지 않다. 정확도는 S/N비, 주파수·위상 추정, 보간, 스윕 선형성, 교정과 설치조건의 영향을 함께 받는다."
      ],
      "rejected_explanations": [
        "대역폭이 작을수록 분해능이 좋아진다고 설명한다.",
        "주파수가 높다는 사실만으로 분해능을 결정한다.",
        "ΔR=c/(2B)를 측정 정확도 또는 FFT bin 간격과 동일시한다."
      ],
      "grading_notes": "대역폭과 반송주파수를 혼동하지 않는지 평가한다. 거리 분해능과 정확도를 구분한다.",
      "source_basis": "Emerson FMCW Technology, Siemens SITRANS manuals and Texas Instruments FMCW radar fundamentals.",
      "claim": "FMCW의 이상적 거리 분해능은 ΔR≈v_g/(2B)이다. 이는 두 인접 반사면을 분리하는 능력이며 단일 표면의 측정 정확도, 반복성 또는 FFT bin 간격과 동일하지 않다. 정확도는 S/N비, 주파수·위상 추정, 보간, 스윕 선형성, 교정과 설치조건의 영향을 함께 받는다.",
      "description": "FMCW의 이상적 거리 분해능은 ΔR≈v_g/(2B)이다. 이는 두 인접 반사면을 분리하는 능력이며 단일 표면의 측정 정확도, 반복성 또는 FFT bin 간격과 동일하지 않다. 정확도는 S/N비, 주파수·위상 추정, 보간, 스윕 선형성, 교정과 설치조건의 영향을 함께 받는다."
    },
    {
      "id": "radar_level_reference_calculation",
      "anchor_id": "radar_level_reference_calculation",
      "statement": "레이더가 측정한 기준점에서 표면까지의 거리 D와 빈 탱크 기준거리 E를 이용하여 레벨은 L=E-D로 계산하며 기준면과 탱크 기준점이 일치해야 한다.",
      "importance": "core",
      "keywords": [
        "측정거리",
        "빈 탱크 거리",
        "L=E-D",
        "안테나 기준면",
        "탱크 기준점"
      ],
      "core_terms": [
        "측정거리",
        "빈 탱크 거리",
        "L=E-D",
        "안테나 기준면",
        "탱크 기준점"
      ],
      "accepted_explanations": [
        "레이더가 직접 측정하는 값은 표면까지 거리임을 설명한다.",
        "기준거리에서 측정거리를 빼 레벨로 환산한다."
      ],
      "rejected_explanations": [
        "거리 D를 그대로 레벨이라고 단정한다.",
        "기준면과 노즐높이를 무시한다."
      ],
      "grading_notes": "거리와 레벨의 방향 및 기준점 정의를 확인한다.",
      "source_basis": "Emerson Rosemount and Siemens SITRANS radar manuals.",
      "claim": "레이더가 측정한 기준점에서 표면까지의 거리 D와 빈 탱크 기준거리 E를 이용하여 레벨은 L=E-D로 계산하며 기준면과 탱크 기준점이 일치해야 한다.",
      "description": "레이더가 측정한 기준점에서 표면까지의 거리 D와 빈 탱크 기준거리 E를 이용하여 레벨은 L=E-D로 계산하며 기준면과 탱크 기준점이 일치해야 한다."
    },
    {
      "id": "radar_dielectric_constant_reflection",
      "anchor_id": "radar_dielectric_constant_reflection",
      "statement": "상대유전율은 경계면 반사계수와 에코강도에 영향을 주며 공기에서 비자성 유전체로 수직입사할 때 전기장 진폭 반사계수는 Γ=(1-√ε_r)/(1+√ε_r)이며, 그 크기는 |Γ|=(√ε_r-1)/(√ε_r+1)이다.",
      "importance": "core",
      "keywords": [
        "상대유전율",
        "반사계수",
        "Γ",
        "에코강도",
        "수직입사",
        "경계면"
      ],
      "core_terms": [
        "상대유전율",
        "반사계수",
        "Γ",
        "에코강도",
        "수직입사",
        "경계면"
      ],
      "accepted_explanations": [
        "공기와 측정물 경계의 임피던스 차이가 반사를 만든다고 설명한다.",
        "유전율 증가가 일반적으로 반사에코 증가에 유리함을 조건부로 설명한다."
      ],
      "rejected_explanations": [
        "유전율이 반사에 전혀 영향을 주지 않는다고 설명한다.",
        "유전율만으로 모든 현장 에코를 결정한다고 단정한다."
      ],
      "grading_notes": "반사계수 식은 이상화된 경계조건이며 실제 설치요인을 함께 고려해야 한다.",
      "source_basis": "Emerson, Siemens, VEGA and Endress+Hauser industrial radar guidance.",
      "claim": "상대유전율은 경계면 반사계수와 에코강도에 영향을 주며 공기에서 비자성 유전체로 수직입사할 때 전기장 진폭 반사계수는 Γ=(1-√ε_r)/(1+√ε_r)이며, 그 크기는 |Γ|=(√ε_r-1)/(√ε_r+1)이다.",
      "description": "상대유전율은 경계면 반사계수와 에코강도에 영향을 주며 공기에서 비자성 유전체로 수직입사할 때 전기장 진폭 반사계수는 Γ=(1-√ε_r)/(1+√ε_r)이며, 그 크기는 |Γ|=(√ε_r-1)/(√ε_r+1)이다."
    },
    {
      "id": "radar_low_dielectric_echo_margin",
      "anchor_id": "radar_low_dielectric_echo_margin",
      "statement": "저유전율 유체나 분체는 반사에코가 약할 수 있으므로 거리, 표면상태, 안테나 이득, 잡음 및 에코마진을 함께 검토해야 한다.",
      "importance": "core",
      "keywords": [
        "저유전율",
        "약한 에코",
        "에코마진",
        "안테나 이득",
        "잡음",
        "적용성"
      ],
      "core_terms": [
        "저유전율",
        "약한 에코",
        "에코마진",
        "안테나 이득",
        "잡음",
        "적용성"
      ],
      "accepted_explanations": [
        "저유전율 매질에서 에코마진 부족 가능성을 설명한다.",
        "표면상태와 거리 및 안테나 조건을 함께 검토한다."
      ],
      "rejected_explanations": [
        "모든 측정물이 동일한 에코를 만든다고 설명한다.",
        "유전율 기준값 하나만으로 적용 가능 여부를 확정한다."
      ],
      "grading_notes": "유전율은 핵심 적용인자이지만 단독 판정기준은 아니다.",
      "source_basis": "Emerson, Siemens, VEGA and Endress+Hauser industrial radar guidance.",
      "claim": "저유전율 유체나 분체는 반사에코가 약할 수 있으므로 거리, 표면상태, 안테나 이득, 잡음 및 에코마진을 함께 검토해야 한다.",
      "description": "저유전율 유체나 분체는 반사에코가 약할 수 있으므로 거리, 표면상태, 안테나 이득, 잡음 및 에코마진을 함께 검토해야 한다."
    },
    {
      "id": "radar_antenna_beam_footprint",
      "anchor_id": "radar_antenna_beam_footprint",
      "statement": "안테나 빔각과 측정거리가 조사면적을 결정하며 빔 경로에 벽, 노즐 또는 내부구조물이 들어오면 허위에코 가능성이 증가한다.",
      "importance": "core",
      "keywords": [
        "안테나",
        "빔각",
        "조사면적",
        "빔 경로",
        "탱크 벽",
        "내부구조물"
      ],
      "core_terms": [
        "안테나",
        "빔각",
        "조사면적",
        "빔 경로",
        "탱크 벽",
        "내부구조물"
      ],
      "accepted_explanations": [
        "거리가 증가할수록 빔 조사영역이 커짐을 설명한다.",
        "빔 경로와 구조물 간 간섭을 설치단계에서 검토한다."
      ],
      "rejected_explanations": [
        "레이더 빔을 폭이 없는 직선으로 설명한다.",
        "벽이나 노즐 반사가 측정에 영향을 주지 않는다고 설명한다."
      ],
      "grading_notes": "빔각, 거리와 탱크 내부구조의 기하관계를 평가한다.",
      "source_basis": "Emerson Rosemount and Siemens SITRANS radar manuals.",
      "claim": "안테나 빔각과 측정거리가 조사면적을 결정하며 빔 경로에 벽, 노즐 또는 내부구조물이 들어오면 허위에코 가능성이 증가한다.",
      "description": "안테나 빔각과 측정거리가 조사면적을 결정하며 빔 경로에 벽, 노즐 또는 내부구조물이 들어오면 허위에코 가능성이 증가한다."
    },
    {
      "id": "radar_frequency_antenna_tradeoff",
      "anchor_id": "radar_frequency_antenna_tradeoff",
      "statement": "같은 안테나 개구에서 높은 반송주파수는 좁은 빔과 소형 안테나 구현에 유리할 수 있다. 다만 FMCW 거리 분해능은 반송주파수 자체가 아니라 유효 변조 대역폭과 신호처리에 의해 결정되며 최대거리, 응축, 부착물, 공정창 및 비용을 함께 고려해야 한다.",
      "importance": "core",
      "keywords": [
        "반송주파수",
        "안테나 개구",
        "좁은 빔",
        "소형 안테나",
        "유효 변조 대역폭",
        "거리 분해능",
        "80 GHz",
        "응축",
        "비용"
      ],
      "core_terms": [
        "반송주파수",
        "안테나 개구",
        "좁은 빔",
        "소형 안테나",
        "유효 변조 대역폭",
        "거리 분해능",
        "80 GHz",
        "응축",
        "비용"
      ],
      "accepted_explanations": [
        "같은 안테나 개구에서 높은 반송주파수의 좁은 빔과 소형 안테나 장점을 설명한다.",
        "FMCW 거리 분해능은 반송주파수 자체가 아니라 유효 변조 대역폭과 신호처리에 의해 결정됨을 설명한다.",
        "최대거리, 응축, 부착물, 공정창 및 비용을 함께 검토한다."
      ],
      "rejected_explanations": [
        "높은 반송주파수 자체가 FMCW 거리 분해능을 결정한다고 설명한다.",
        "주파수가 높을수록 모든 조건에서 측정거리가 무조건 길어진다고 설명한다.",
        "안테나 크기와 빔각의 관계를 무시한다."
      ],
      "grading_notes": "반송주파수의 빔·안테나 특성과 유효 변조 대역폭의 거리 분해능 역할을 명확히 구분하는지 평가한다.",
      "source_basis": "Emerson FMCW Technology, Siemens SITRANS manuals and Texas Instruments FMCW radar fundamentals.",
      "claim": "같은 안테나 개구에서 높은 반송주파수는 좁은 빔과 소형 안테나 구현에 유리할 수 있다. 다만 FMCW 거리 분해능은 반송주파수 자체가 아니라 유효 변조 대역폭과 신호처리에 의해 결정되며 최대거리, 응축, 부착물, 공정창 및 비용을 함께 고려해야 한다.",
      "description": "같은 안테나 개구에서 높은 반송주파수는 좁은 빔과 소형 안테나 구현에 유리할 수 있다. 다만 FMCW 거리 분해능은 반송주파수 자체가 아니라 유효 변조 대역폭과 신호처리에 의해 결정되며 최대거리, 응축, 부착물, 공정창 및 비용을 함께 고려해야 한다."
    },
    {
      "id": "radar_blocking_distance_near_field",
      "anchor_id": "radar_blocking_distance_near_field",
      "statement": "송신 누설, 수신기 포화, 내부반사 및 근거리 신호처리 한계로 블로킹 거리 또는 최소 측정거리가 발생할 수 있으며 최대레벨이 이 구간에 들어가지 않도록 해야 한다.",
      "importance": "core",
      "keywords": [
        "블로킹 거리",
        "불감대",
        "송신 누설",
        "수신기 포화",
        "내부반사",
        "최소 측정거리"
      ],
      "core_terms": [
        "블로킹 거리",
        "불감대",
        "송신 누설",
        "수신기 포화",
        "내부반사",
        "최소 측정거리"
      ],
      "accepted_explanations": [
        "안테나 부근에서 정상 에코분리가 어려운 원인을 설명한다.",
        "최대레벨과 블로킹 거리 사이의 설치여유를 확보한다."
      ],
      "rejected_explanations": [
        "안테나 바로 앞까지 항상 측정 가능하다고 설명한다.",
        "블로킹 거리를 탱크 전체 측정범위와 동일시한다."
      ],
      "grading_notes": "기기별 최소거리와 노즐조건을 제조사 자료로 확인해야 한다.",
      "source_basis": "Emerson Rosemount and Siemens SITRANS radar manuals.",
      "claim": "송신 누설, 수신기 포화, 내부반사 및 근거리 신호처리 한계로 블로킹 거리 또는 최소 측정거리가 발생할 수 있으며 최대레벨이 이 구간에 들어가지 않도록 해야 한다.",
      "description": "송신 누설, 수신기 포화, 내부반사 및 근거리 신호처리 한계로 블로킹 거리 또는 최소 측정거리가 발생할 수 있으며 최대레벨이 이 구간에 들어가지 않도록 해야 한다."
    },
    {
      "id": "radar_false_echo_multiple_reflection",
      "anchor_id": "radar_false_echo_multiple_reflection",
      "statement": "노즐, 탱크 벽, 교반기, 보강재 및 가열코일은 허위에코를 만들 수 있고 탱크 구조와 표면 사이의 다중반사는 잘못된 거리피크를 만들 수 있다.",
      "importance": "core",
      "keywords": [
        "허위에코",
        "다중반사",
        "노즐",
        "교반기",
        "가열코일",
        "거리피크"
      ],
      "core_terms": [
        "허위에코",
        "다중반사",
        "노즐",
        "교반기",
        "가열코일",
        "거리피크"
      ],
      "accepted_explanations": [
        "고정구조물 반사와 실제 표면에코를 구분한다.",
        "다중경로 반사로 실제거리와 다른 피크가 생길 수 있음을 설명한다."
      ],
      "rejected_explanations": [
        "가장 큰 에코가 항상 실제 표면이라고 단정한다.",
        "레이더에는 허위에코가 존재하지 않는다고 설명한다."
      ],
      "grading_notes": "설치개선과 에코맵 및 거리창을 함께 대책으로 제시한다.",
      "source_basis": "Emerson Rosemount and Siemens SITRANS radar manuals.",
      "claim": "노즐, 탱크 벽, 교반기, 보강재 및 가열코일은 허위에코를 만들 수 있고 탱크 구조와 표면 사이의 다중반사는 잘못된 거리피크를 만들 수 있다.",
      "description": "노즐, 탱크 벽, 교반기, 보강재 및 가열코일은 허위에코를 만들 수 있고 탱크 구조와 표면 사이의 다중반사는 잘못된 거리피크를 만들 수 있다."
    },
    {
      "id": "radar_surface_foam_turbulence_slope",
      "anchor_id": "radar_surface_foam_turbulence_slope",
      "statement": "거품, 난류, 파동 및 경사진 분체표면은 에코의 방향·진폭·분포를 변화시키며 필터와 평균화는 응답속도와 안정성의 절충을 가진다.",
      "importance": "core",
      "keywords": [
        "거품",
        "난류",
        "파동",
        "경사면",
        "분체",
        "평균화"
      ],
      "core_terms": [
        "거품",
        "난류",
        "파동",
        "경사면",
        "분체",
        "평균화"
      ],
      "accepted_explanations": [
        "표면형상이 확산반사와 에코변동을 만든다고 설명한다.",
        "추적필터의 안정성과 응답속도 절충을 설명한다."
      ],
      "rejected_explanations": [
        "거품과 난류가 모든 레이더에서 항상 무관하다고 설명한다.",
        "평균화를 늘리면 응답속도도 항상 빨라진다고 설명한다."
      ],
      "grading_notes": "측정물과 주파수 및 표면상태에 따라 영향이 달라짐을 인정한다.",
      "source_basis": "Emerson Rosemount and Siemens SITRANS radar manuals.",
      "claim": "거품, 난류, 파동 및 경사진 분체표면은 에코의 방향·진폭·분포를 변화시키며 필터와 평균화는 응답속도와 안정성의 절충을 가진다.",
      "description": "거품, 난류, 파동 및 경사진 분체표면은 에코의 방향·진폭·분포를 변화시키며 필터와 평균화는 응답속도와 안정성의 절충을 가진다."
    },
    {
      "id": "radar_vapor_pressure_temperature_effect",
      "anchor_id": "radar_vapor_pressure_temperature_effect",
      "statement": "일반적인 증기와 온도변화의 영향은 초음파식보다 작을 수 있으나 고압가스, 고밀도 증기, 응축 및 특수 가스층의 영향까지 항상 0이라고 단정할 수 없다.",
      "importance": "core",
      "keywords": [
        "증기",
        "고압가스",
        "온도",
        "응축",
        "가스층",
        "전파특성"
      ],
      "core_terms": [
        "증기",
        "고압가스",
        "온도",
        "응축",
        "가스층",
        "전파특성"
      ],
      "accepted_explanations": [
        "일반 공정에서 온도에 따른 음속보상이 필요하지 않다는 차이를 설명한다.",
        "고압·고밀도 가스와 응축의 영향을 조건부로 검토한다."
      ],
      "rejected_explanations": [
        "모든 온도·압력·증기조건에서 전파와 에코가 절대 불변이라고 설명한다.",
        "레이더에 초음파식 온도보상식을 적용한다."
      ],
      "grading_notes": "영향이 상대적으로 작다는 표현과 영향이 전혀 없다는 표현을 구분한다.",
      "source_basis": "Emerson Rosemount and Siemens SITRANS radar manuals.",
      "claim": "일반적인 증기와 온도변화의 영향은 초음파식보다 작을 수 있으나 고압가스, 고밀도 증기, 응축 및 특수 가스층의 영향까지 항상 0이라고 단정할 수 없다.",
      "description": "일반적인 증기와 온도변화의 영향은 초음파식보다 작을 수 있으나 고압가스, 고밀도 증기, 응축 및 특수 가스층의 영향까지 항상 0이라고 단정할 수 없다."
    },
    {
      "id": "radar_mounting_nozzle_obstruction_error",
      "anchor_id": "radar_mounting_nozzle_obstruction_error",
      "statement": "긴 노즐, 작은 노즐직경, 안테나 매몰, 빔 경로 장애물 및 측정면을 향하지 않은 부적절한 정렬은 측정오차를 유발한다. 액체에서는 일반적으로 안테나 축을 액면에 수직으로 정렬하고, 분체에서는 경사진 표면을 향하도록 제조사 지침과 정렬장치에 따라 의도적으로 기울일 수 있다.",
      "importance": "core",
      "keywords": [
        "노즐",
        "안테나 돌출",
        "액면 수직 정렬",
        "분체 표면방향 정렬",
        "정렬장치",
        "장애물",
        "빔 경로",
        "설치오차"
      ],
      "core_terms": [
        "노즐",
        "안테나 돌출",
        "액면 수직 정렬",
        "분체 표면방향 정렬",
        "정렬장치",
        "장애물",
        "빔 경로",
        "설치오차"
      ],
      "accepted_explanations": [
        "노즐 내부반사와 빔 차폐 및 측정면을 향하지 않은 부적절한 정렬의 원인을 설명한다.",
        "액체에서는 일반적으로 안테나 축을 액면에 수직으로 정렬한다.",
        "분체에서는 제조사 지침과 정렬장치에 따라 경사진 표면을 향하도록 의도적으로 기울일 수 있음을 설명한다."
      ],
      "rejected_explanations": [
        "노즐 길이와 직경이 측정에 무관하다고 설명한다.",
        "액체와 분체에 동일한 안테나 정렬조건을 무조건 적용한다.",
        "분체 표면을 향한 의도적 경사 정렬을 항상 설치오차로 판정한다."
      ],
      "grading_notes": "액체의 수직 정렬 원칙과 분체의 표면방향 정렬 가능성을 구분하고 제조사 설치기준을 적용하는지 평가한다.",
      "source_basis": "Emerson Rosemount and Siemens SITRANS radar manuals.",
      "claim": "긴 노즐, 작은 노즐직경, 안테나 매몰, 빔 경로 장애물 및 측정면을 향하지 않은 부적절한 정렬은 측정오차를 유발한다. 액체에서는 일반적으로 안테나 축을 액면에 수직으로 정렬하고, 분체에서는 경사진 표면을 향하도록 제조사 지침과 정렬장치에 따라 의도적으로 기울일 수 있다.",
      "description": "긴 노즐, 작은 노즐직경, 안테나 매몰, 빔 경로 장애물 및 측정면을 향하지 않은 부적절한 정렬은 측정오차를 유발한다. 액체에서는 일반적으로 안테나 축을 액면에 수직으로 정렬하고, 분체에서는 경사진 표면을 향하도록 제조사 지침과 정렬장치에 따라 의도적으로 기울일 수 있다."
    },
    {
      "id": "radar_antenna_buildup_condensation",
      "anchor_id": "radar_antenna_buildup_condensation",
      "statement": "안테나의 부착물, 코팅, 응축 및 결로는 송수신 손실과 허위에코를 증가시킬 수 있으므로 퍼지, 가열, 적절한 재질과 예방정비를 검토한다.",
      "importance": "core",
      "keywords": [
        "안테나 부착물",
        "코팅",
        "응축",
        "결로",
        "퍼지",
        "예방정비"
      ],
      "core_terms": [
        "안테나 부착물",
        "코팅",
        "응축",
        "결로",
        "퍼지",
        "예방정비"
      ],
      "accepted_explanations": [
        "안테나 표면 오염이 신호손실과 반사를 만든다고 설명한다.",
        "공정조건에 따라 퍼지·가열·세척·재질선정을 적용한다."
      ],
      "rejected_explanations": [
        "안테나 오염이 전자기파에 영향을 주지 않는다고 설명한다.",
        "소프트웨어 필터만으로 모든 부착문제를 해결한다고 설명한다."
      ],
      "grading_notes": "유지보수성과 설치환경을 방식선정에 포함한다.",
      "source_basis": "Emerson Rosemount and Siemens SITRANS radar manuals.",
      "claim": "안테나의 부착물, 코팅, 응축 및 결로는 송수신 손실과 허위에코를 증가시킬 수 있으므로 퍼지, 가열, 적절한 재질과 예방정비를 검토한다.",
      "description": "안테나의 부착물, 코팅, 응축 및 결로는 송수신 손실과 허위에코를 증가시킬 수 있으므로 퍼지, 가열, 적절한 재질과 예방정비를 검토한다."
    },
    {
      "id": "radar_echo_mapping_calibration_diagnostics",
      "anchor_id": "radar_echo_mapping_calibration_diagnostics",
      "statement": "시운전 시 기준거리, 실제 레벨, 에코곡선, 에코마진과 허위에코 맵을 확인하고 거리창, 임계값, 추적설정 및 진단정보를 공정조건에 맞게 조정한다.",
      "importance": "core",
      "keywords": [
        "시운전",
        "교정",
        "에코곡선",
        "에코마진",
        "허위에코 맵",
        "진단"
      ],
      "core_terms": [
        "시운전",
        "교정",
        "에코곡선",
        "에코마진",
        "허위에코 맵",
        "진단"
      ],
      "accepted_explanations": [
        "빈 탱크 또는 알려진 레벨에서 기준거리와 출력값을 확인한다.",
        "에코맵과 진단정보를 이용해 실제 표면에코를 검증한다."
      ],
      "rejected_explanations": [
        "설치 후 기준값 확인 없이 자동설정만으로 완료한다.",
        "허위에코 맵을 실제 표면에코 삭제용으로 무조건 사용한다."
      ],
      "grading_notes": "교정, 에코해석 및 공정상태 확인을 하나의 시운전 절차로 평가한다.",
      "source_basis": "Emerson Rosemount and Siemens SITRANS radar manuals.",
      "claim": "시운전 시 기준거리, 실제 레벨, 에코곡선, 에코마진과 허위에코 맵을 확인하고 거리창, 임계값, 추적설정 및 진단정보를 공정조건에 맞게 조정한다.",
      "description": "시운전 시 기준거리, 실제 레벨, 에코곡선, 에코마진과 허위에코 맵을 확인하고 거리창, 임계값, 추적설정 및 진단정보를 공정조건에 맞게 조정한다."
    },
    {
      "id": "radar_pulse_fmcw_application_selection",
      "anchor_id": "radar_pulse_fmcw_application_selection",
      "statement": "펄스식은 왕복시간을, FMCW식은 스윕 기울기와 비트주파수를 이용하며 방식 선정은 거리, 분해능, 유전율, 공정조건, 설치공간, 기존설비 연계 및 비용을 기준으로 한다.",
      "importance": "core",
      "keywords": [
        "펄스식",
        "FMCW식",
        "GWR",
        "초음파식",
        "방식선정",
        "기존설비 연계"
      ],
      "core_terms": [
        "펄스식",
        "FMCW식",
        "GWR",
        "초음파식",
        "방식선정",
        "기존설비 연계"
      ],
      "accepted_explanations": [
        "두 레이더 방식의 직접 측정변수를 구분한다.",
        "GWR·초음파식과의 적용조건 및 비용을 함께 비교한다."
      ],
      "rejected_explanations": [
        "한 방식이 모든 공정에서 절대적으로 우수하다고 설명한다.",
        "기존 노즐·전원·통신·유지보수 체계를 무시한다."
      ],
      "grading_notes": "기술적 성능과 현장 적용성 및 생애주기비용을 함께 평가한다.",
      "source_basis": "Emerson Rosemount and Siemens SITRANS radar manuals.",
      "claim": "펄스식은 왕복시간을, FMCW식은 스윕 기울기와 비트주파수를 이용하며 방식 선정은 거리, 분해능, 유전율, 공정조건, 설치공간, 기존설비 연계 및 비용을 기준으로 한다.",
      "description": "펄스식은 왕복시간을, FMCW식은 스윕 기울기와 비트주파수를 이용하며 방식 선정은 거리, 분해능, 유전율, 공정조건, 설치공간, 기존설비 연계 및 비용을 기준으로 한다."
    },
    {
      "id": "radar_point_target_equation_scope",
      "anchor_id": "radar_point_target_equation_scope",
      "statement": "단일 점표적 monostatic radar equation의 R⁻⁴ 관계는 링크 예산의 참고식이다. 탱크 액면과 분체표면은 안테나 빔 footprint를 가진 확장 반사면이므로 R⁻⁴를 레벨계의 보편 지배식으로 적용하지 않고 안테나 패턴, 표면 거칠기·기울기, 유전율과 수신처리를 함께 평가한다.",
      "importance": "core",
      "keywords": [
        "radar equation",
        "point target",
        "R⁻⁴",
        "확장 반사면",
        "link budget"
      ],
      "core_terms": [
        "radar equation",
        "point target",
        "R⁻⁴",
        "확장 반사면",
        "link budget"
      ],
      "accepted_explanations": [
        "단일 점표적 monostatic radar equation의 R⁻⁴ 관계는 링크 예산의 참고식이다. 탱크 액면과 분체표면은 안테나 빔 footprint를 가진 확장 반사면이므로 R⁻⁴를 레벨계의 보편 지배식으로 적용하지 않고 안테나 패턴, 표면 거칠기·기울기, 유전율과 수신처리를 함께 평가한다."
      ],
      "rejected_explanations": [
        "탱크 액면 수신전력이 모든 조건에서 정확히 R⁻⁴로 감소한다고 단정한다."
      ],
      "grading_notes": "점표적과 확장 액면의 적용범위를 구분한다.",
      "source_basis": "Texas Instruments radar fundamentals and industrial radar level guidance.",
      "claim": "단일 점표적 monostatic radar equation의 R⁻⁴ 관계는 링크 예산의 참고식이다. 탱크 액면과 분체표면은 안테나 빔 footprint를 가진 확장 반사면이므로 R⁻⁴를 레벨계의 보편 지배식으로 적용하지 않고 안테나 패턴, 표면 거칠기·기울기, 유전율과 수신처리를 함께 평가한다.",
      "description": "단일 점표적 monostatic radar equation의 R⁻⁴ 관계는 링크 예산의 참고식이다. 탱크 액면과 분체표면은 안테나 빔 footprint를 가진 확장 반사면이므로 R⁻⁴를 레벨계의 보편 지배식으로 적용하지 않고 안테나 패턴, 표면 거칠기·기울기, 유전율과 수신처리를 함께 평가한다.",
      "topic_id": "radar_level_gauge_fmcw_pulse_distance_level_dielectric_constant_false_echo_installation_error"
    },
    {
      "id": "radar_echo_polarity_sign_convention",
      "anchor_id": "radar_echo_polarity_sign_convention",
      "statement": "공기에서 비자성 고유전율 매질로 수직입사할 때 전기장 반사계수 Γ=(1-√ε_r)/(1+√ε_r)는 음수이므로 이상적 전기장 반사에는 위상반전이 있다. 다만 계기가 표시하는 에코곡선의 부호와 극성은 수신기·복조·표시 규약에 따라 달라질 수 있으므로 피크 부호만으로 제품표면과 구조물을 보편적으로 판정하지 않는다.",
      "importance": "core",
      "keywords": [
        "반사계수",
        "위상반전",
        "에코 극성",
        "표시 규약"
      ],
      "core_terms": [
        "반사계수",
        "위상반전",
        "에코 극성",
        "표시 규약"
      ],
      "accepted_explanations": [
        "공기에서 비자성 고유전율 매질로 수직입사할 때 전기장 반사계수 Γ=(1-√ε_r)/(1+√ε_r)는 음수이므로 이상적 전기장 반사에는 위상반전이 있다. 다만 계기가 표시하는 에코곡선의 부호와 극성은 수신기·복조·표시 규약에 따라 달라질 수 있으므로 피크 부호만으로 제품표면과 구조물을 보편적으로 판정하지 않는다."
      ],
      "rejected_explanations": [
        "모든 제조사에서 피크 부호만으로 제품표면과 구조물을 결정론적으로 구분한다."
      ],
      "grading_notes": "물리적 반사계수와 표시극성을 구분한다.",
      "source_basis": "Electromagnetic boundary theory and Emerson, Siemens and VEGA echo-processing guidance.",
      "claim": "공기에서 비자성 고유전율 매질로 수직입사할 때 전기장 반사계수 Γ=(1-√ε_r)/(1+√ε_r)는 음수이므로 이상적 전기장 반사에는 위상반전이 있다. 다만 계기가 표시하는 에코곡선의 부호와 극성은 수신기·복조·표시 규약에 따라 달라질 수 있으므로 피크 부호만으로 제품표면과 구조물을 보편적으로 판정하지 않는다.",
      "description": "공기에서 비자성 고유전율 매질로 수직입사할 때 전기장 반사계수 Γ=(1-√ε_r)/(1+√ε_r)는 음수이므로 이상적 전기장 반사에는 위상반전이 있다. 다만 계기가 표시하는 에코곡선의 부호와 극성은 수신기·복조·표시 규약에 따라 달라질 수 있으므로 피크 부호만으로 제품표면과 구조물을 보편적으로 판정하지 않는다.",
      "topic_id": "radar_level_gauge_fmcw_pulse_distance_level_dielectric_constant_false_echo_installation_error"
    },
    {
      "id": "radar_adaptive_threshold_echo_tracking",
      "anchor_id": "radar_adaptive_threshold_echo_tracking",
      "statement": "에코 임계값은 거리별 잡음과 감쇠를 고려하여 유효 에코를 선별하는 진폭 기준이다. 고정 또는 적응형 임계곡선, false-echo map, 거리창, 에코 이력과 추적 알고리즘을 함께 사용하며 단일 최대피크만으로 실제 표면을 확정하지 않는다.",
      "importance": "core",
      "keywords": [
        "threshold",
        "false-echo map",
        "거리창",
        "echo tracking",
        "에코 이력"
      ],
      "core_terms": [
        "threshold",
        "false-echo map",
        "거리창",
        "echo tracking",
        "에코 이력"
      ],
      "accepted_explanations": [
        "에코 임계값은 거리별 잡음과 감쇠를 고려하여 유효 에코를 선별하는 진폭 기준이다. 고정 또는 적응형 임계곡선, false-echo map, 거리창, 에코 이력과 추적 알고리즘을 함께 사용하며 단일 최대피크만으로 실제 표면을 확정하지 않는다."
      ],
      "rejected_explanations": [
        "한 시점의 최대 진폭 피크를 항상 실제 액면으로 선정한다."
      ],
      "grading_notes": "임계곡선과 에코 추적을 함께 평가한다.",
      "source_basis": "Emerson Rosemount and Siemens SITRANS radar manuals.",
      "claim": "에코 임계값은 거리별 잡음과 감쇠를 고려하여 유효 에코를 선별하는 진폭 기준이다. 고정 또는 적응형 임계곡선, false-echo map, 거리창, 에코 이력과 추적 알고리즘을 함께 사용하며 단일 최대피크만으로 실제 표면을 확정하지 않는다.",
      "description": "에코 임계값은 거리별 잡음과 감쇠를 고려하여 유효 에코를 선별하는 진폭 기준이다. 고정 또는 적응형 임계곡선, false-echo map, 거리창, 에코 이력과 추적 알고리즘을 함께 사용하며 단일 최대피크만으로 실제 표면을 확정하지 않는다.",
      "topic_id": "radar_level_gauge_fmcw_pulse_distance_level_dielectric_constant_false_echo_installation_error"
    },
    {
      "id": "radar_upper_null_zone_overfill_coordination",
      "anchor_id": "radar_upper_null_zone_overfill_coordination",
      "statement": "안테나 근처에는 송신누설, 링다운, 노즐반사와 수신기 포화로 blocking distance 또는 upper null zone이 생길 수 있다. 과도한 마스킹은 실제 고레벨을 숨길 수 있으므로 최대 운전레벨과 독립 HH 과충전 방호가 불감영역 밖에서 성립하도록 조정한다.",
      "importance": "core",
      "keywords": [
        "upper null zone",
        "blocking distance",
        "최대레벨",
        "HH alarm",
        "과충전 방호"
      ],
      "core_terms": [
        "upper null zone",
        "blocking distance",
        "최대레벨",
        "HH alarm",
        "과충전 방호"
      ],
      "accepted_explanations": [
        "안테나 근처에는 송신누설, 링다운, 노즐반사와 수신기 포화로 blocking distance 또는 upper null zone이 생길 수 있다. 과도한 마스킹은 실제 고레벨을 숨길 수 있으므로 최대 운전레벨과 독립 HH 과충전 방호가 불감영역 밖에서 성립하도록 조정한다."
      ],
      "rejected_explanations": [
        "상부 불감대를 확대해도 고레벨과 과충전 방호에 영향이 없다고 설명한다."
      ],
      "grading_notes": "근거리 제한과 독립 HH 방호를 평가한다.",
      "source_basis": "Emerson Rosemount and Siemens SITRANS radar manuals.",
      "claim": "안테나 근처에는 송신누설, 링다운, 노즐반사와 수신기 포화로 blocking distance 또는 upper null zone이 생길 수 있다. 과도한 마스킹은 실제 고레벨을 숨길 수 있으므로 최대 운전레벨과 독립 HH 과충전 방호가 불감영역 밖에서 성립하도록 조정한다.",
      "description": "안테나 근처에는 송신누설, 링다운, 노즐반사와 수신기 포화로 blocking distance 또는 upper null zone이 생길 수 있다. 과도한 마스킹은 실제 고레벨을 숨길 수 있으므로 최대 운전레벨과 독립 HH 과충전 방호가 불감영역 밖에서 성립하도록 조정한다.",
      "topic_id": "radar_level_gauge_fmcw_pulse_distance_level_dielectric_constant_false_echo_installation_error"
    },
    {
      "id": "gwr_tdr_guided_wave_principle",
      "anchor_id": "gwr_tdr_guided_wave_principle",
      "statement": "일반적인 산업용 GWR은 TDR 원리에 따라 저전력 나노초 마이크로파 펄스를 rod, cable 또는 coaxial probe를 따라 전송하고 임피던스가 변하는 제품표면의 반사 왕복시간으로 거리를 계산한다. 이를 자유공간 FMCW와 동일한 구조로 일반화하지 않는다.",
      "importance": "core",
      "keywords": [
        "GWR",
        "TDR",
        "나노초 펄스",
        "probe",
        "임피던스 변화"
      ],
      "core_terms": [
        "GWR",
        "TDR",
        "나노초 펄스",
        "probe",
        "임피던스 변화"
      ],
      "accepted_explanations": [
        "일반적인 산업용 GWR은 TDR 원리에 따라 저전력 나노초 마이크로파 펄스를 rod, cable 또는 coaxial probe를 따라 전송하고 임피던스가 변하는 제품표면의 반사 왕복시간으로 거리를 계산한다. 이를 자유공간 FMCW와 동일한 구조로 일반화하지 않는다."
      ],
      "rejected_explanations": [
        "모든 GWR이 자유공간 FMCW 처프와 FFT로 거리를 계산한다고 설명한다."
      ],
      "grading_notes": "GWR TDR과 자유공간 FMCW를 구분한다.",
      "source_basis": "Emerson Rosemount 5300 and Endress+Hauser Levelflex.",
      "claim": "일반적인 산업용 GWR은 TDR 원리에 따라 저전력 나노초 마이크로파 펄스를 rod, cable 또는 coaxial probe를 따라 전송하고 임피던스가 변하는 제품표면의 반사 왕복시간으로 거리를 계산한다. 이를 자유공간 FMCW와 동일한 구조로 일반화하지 않는다.",
      "description": "일반적인 산업용 GWR은 TDR 원리에 따라 저전력 나노초 마이크로파 펄스를 rod, cable 또는 coaxial probe를 따라 전송하고 임피던스가 변하는 제품표면의 반사 왕복시간으로 거리를 계산한다. 이를 자유공간 FMCW와 동일한 구조로 일반화하지 않는다.",
      "topic_id": "radar_level_gauge_fmcw_pulse_distance_level_dielectric_constant_false_echo_installation_error"
    },
    {
      "id": "gwr_effective_permittivity_propagation_path",
      "anchor_id": "gwr_effective_permittivity_propagation_path",
      "statement": "GWR의 상부 액면 레벨은 기준점부터 표면까지의 기체·증기 구간 왕복시간으로 계산하므로 제품 액체의 √ε_r를 거리식 전체에 일률적으로 나누지 않는다. 계면 측정에서는 펄스가 상부 액체층을 통과하므로 그 구간의 전파속도 c_0/√ε_r,upper와 상부층 두께를 반영한다.",
      "importance": "core",
      "keywords": [
        "GWR 거리식",
        "전파경로",
        "상부 액체",
        "유전율",
        "계면 측정"
      ],
      "core_terms": [
        "GWR 거리식",
        "전파경로",
        "상부 액체",
        "유전율",
        "계면 측정"
      ],
      "accepted_explanations": [
        "GWR의 상부 액면 레벨은 기준점부터 표면까지의 기체·증기 구간 왕복시간으로 계산하므로 제품 액체의 √ε_r를 거리식 전체에 일률적으로 나누지 않는다. 계면 측정에서는 펄스가 상부 액체층을 통과하므로 그 구간의 전파속도 c_0/√ε_r,upper와 상부층 두께를 반영한다."
      ],
      "rejected_explanations": [
        "GWR 상부 액면 거리식 전체에 제품 액체의 √ε_r를 일률 적용한다.",
        "계면 측정에서 상부 액체층 전파지연을 무시한다."
      ],
      "grading_notes": "상부 액면과 계면 측정의 전파경로를 구분한다.",
      "source_basis": "Emerson and Endress+Hauser GWR interface guidance.",
      "claim": "GWR의 상부 액면 레벨은 기준점부터 표면까지의 기체·증기 구간 왕복시간으로 계산하므로 제품 액체의 √ε_r를 거리식 전체에 일률적으로 나누지 않는다. 계면 측정에서는 펄스가 상부 액체층을 통과하므로 그 구간의 전파속도 c_0/√ε_r,upper와 상부층 두께를 반영한다.",
      "description": "GWR의 상부 액면 레벨은 기준점부터 표면까지의 기체·증기 구간 왕복시간으로 계산하므로 제품 액체의 √ε_r를 거리식 전체에 일률적으로 나누지 않는다. 계면 측정에서는 펄스가 상부 액체층을 통과하므로 그 구간의 전파속도 c_0/√ε_r,upper와 상부층 두께를 반영한다.",
      "topic_id": "radar_level_gauge_fmcw_pulse_distance_level_dielectric_constant_false_echo_installation_error"
    },
    {
      "id": "gwr_quasi_tem_return_path",
      "anchor_id": "gwr_quasi_tem_return_path",
      "statement": "동축 또는 2선식 프로브는 이상적 TEM 전파를 근사할 수 있다. 단일 rod·cable probe는 탱크벽, 노즐과 주변 구조가 귀환경로를 형성하는 실용적 guided 또는 quasi-TEM 구조이므로 항상 완전한 무분산 TEM이라고 단정하지 않는다. 연결부, 프로브 형상과 부착물은 링잉·감쇠·허위에코를 발생시킬 수 있다.",
      "importance": "core",
      "keywords": [
        "TEM",
        "quasi-TEM",
        "귀환경로",
        "single probe",
        "ringing"
      ],
      "core_terms": [
        "TEM",
        "quasi-TEM",
        "귀환경로",
        "single probe",
        "ringing"
      ],
      "accepted_explanations": [
        "동축 또는 2선식 프로브는 이상적 TEM 전파를 근사할 수 있다. 단일 rod·cable probe는 탱크벽, 노즐과 주변 구조가 귀환경로를 형성하는 실용적 guided 또는 quasi-TEM 구조이므로 항상 완전한 무분산 TEM이라고 단정하지 않는다. 연결부, 프로브 형상과 부착물은 링잉·감쇠·허위에코를 발생시킬 수 있다."
      ],
      "rejected_explanations": [
        "단일 rod probe가 탱크 구조와 무관한 완전한 무분산 TEM 선로라고 설명한다."
      ],
      "grading_notes": "이상적 TEM과 실제 귀환경로를 구분한다.",
      "source_basis": "Guided-wave transmission-line theory and manufacturer probe installation guidance.",
      "claim": "동축 또는 2선식 프로브는 이상적 TEM 전파를 근사할 수 있다. 단일 rod·cable probe는 탱크벽, 노즐과 주변 구조가 귀환경로를 형성하는 실용적 guided 또는 quasi-TEM 구조이므로 항상 완전한 무분산 TEM이라고 단정하지 않는다. 연결부, 프로브 형상과 부착물은 링잉·감쇠·허위에코를 발생시킬 수 있다.",
      "description": "동축 또는 2선식 프로브는 이상적 TEM 전파를 근사할 수 있다. 단일 rod·cable probe는 탱크벽, 노즐과 주변 구조가 귀환경로를 형성하는 실용적 guided 또는 quasi-TEM 구조이므로 항상 완전한 무분산 TEM이라고 단정하지 않는다. 연결부, 프로브 형상과 부착물은 링잉·감쇠·허위에코를 발생시킬 수 있다.",
      "topic_id": "radar_level_gauge_fmcw_pulse_distance_level_dielectric_constant_false_echo_installation_error"
    },
    {
      "id": "gwr_interface_and_process_limitations",
      "anchor_id": "gwr_interface_and_process_limitations",
      "statement": "GWR은 자유공간 레이더보다 좁은 공간, 내부구조물, 난류와 일부 거품 조건에 유리할 수 있지만 공정 영향에 면역인 것은 아니다. 저유전율, 두꺼운 거품·에멀전, 프로브 부착물, 인장하중, 휨·접촉, 고압증기와 상·하부 매질의 유전율 차이를 검토한다.",
      "importance": "core",
      "keywords": [
        "foam",
        "buildup",
        "인장하중",
        "고압증기",
        "interface",
        "유전율 차이"
      ],
      "core_terms": [
        "foam",
        "buildup",
        "인장하중",
        "고압증기",
        "interface",
        "유전율 차이"
      ],
      "accepted_explanations": [
        "GWR은 자유공간 레이더보다 좁은 공간, 내부구조물, 난류와 일부 거품 조건에 유리할 수 있지만 공정 영향에 면역인 것은 아니다. 저유전율, 두꺼운 거품·에멀전, 프로브 부착물, 인장하중, 휨·접촉, 고압증기와 상·하부 매질의 유전율 차이를 검토한다."
      ],
      "rejected_explanations": [
        "GWR은 거품, 부착물, 증기와 기계적 하중의 영향을 절대로 받지 않는다고 설명한다."
      ],
      "grading_notes": "GWR 장점과 공정·기계적 한계를 함께 평가한다.",
      "source_basis": "Emerson, Endress+Hauser and VEGA GWR application guidance.",
      "claim": "GWR은 자유공간 레이더보다 좁은 공간, 내부구조물, 난류와 일부 거품 조건에 유리할 수 있지만 공정 영향에 면역인 것은 아니다. 저유전율, 두꺼운 거품·에멀전, 프로브 부착물, 인장하중, 휨·접촉, 고압증기와 상·하부 매질의 유전율 차이를 검토한다.",
      "description": "GWR은 자유공간 레이더보다 좁은 공간, 내부구조물, 난류와 일부 거품 조건에 유리할 수 있지만 공정 영향에 면역인 것은 아니다. 저유전율, 두꺼운 거품·에멀전, 프로브 부착물, 인장하중, 휨·접촉, 고압증기와 상·하부 매질의 유전율 차이를 검토한다.",
      "topic_id": "radar_level_gauge_fmcw_pulse_distance_level_dielectric_constant_false_echo_installation_error"
    }
  ],
  "fatal_wrong_claims": [
    {
      "id": "radar_fatal_sound_speed_principle",
      "claim": "레이더식 레벨계는 공기 중 음속을 이용한다.",
      "correction": "레이더식은 전자기파를 이용하며 기체공간에서 전파속도는 대체로 광속에 가깝다.",
      "wrong_claim": "레이더식 레벨계는 공기 중 음속을 이용한다.",
      "correct_rule": "레이더식은 전자기파를 이용하며 기체공간에서 전파속도는 대체로 광속에 가깝다.",
      "severity": "fatal",
      "affected_layers": [
        "B",
        "C"
      ],
      "message": "오류: 레이더식 레벨계는 공기 중 음속을 이용한다. 정정: 레이더식은 전자기파를 이용하며 기체공간에서 전파속도는 대체로 광속에 가깝다.",
      "description": "오류: 레이더식 레벨계는 공기 중 음속을 이용한다. 정정: 레이더식은 전자기파를 이용하며 기체공간에서 전파속도는 대체로 광속에 가깝다.",
      "grading_notes": "오류: 레이더식 레벨계는 공기 중 음속을 이용한다. 정정: 레이더식은 전자기파를 이용하며 기체공간에서 전파속도는 대체로 광속에 가깝다."
    },
    {
      "id": "radar_fatal_no_round_trip_half",
      "claim": "펄스의 왕복시간에 광속을 곱한 값이 그대로 편도거리이다.",
      "correction": "왕복경로이므로 D=cτ/2로 계산한다.",
      "wrong_claim": "펄스의 왕복시간에 광속을 곱한 값이 그대로 편도거리이다.",
      "correct_rule": "왕복경로이므로 D=cτ/2로 계산한다.",
      "severity": "fatal",
      "affected_layers": [
        "B",
        "C"
      ],
      "message": "오류: 펄스의 왕복시간에 광속을 곱한 값이 그대로 편도거리이다. 정정: 왕복경로이므로 D=cτ/2로 계산한다.",
      "description": "오류: 펄스의 왕복시간에 광속을 곱한 값이 그대로 편도거리이다. 정정: 왕복경로이므로 D=cτ/2로 계산한다.",
      "grading_notes": "오류: 펄스의 왕복시간에 광속을 곱한 값이 그대로 편도거리이다. 정정: 왕복경로이므로 D=cτ/2로 계산한다."
    },
    {
      "id": "radar_fatal_fmcw_direct_time_only",
      "claim": "FMCW식은 펄스식과 동일하게 송수신 시각만 직접 측정한다.",
      "correction": "FMCW식은 주파수 스윕과 지연된 수신파의 비트주파수를 이용한다.",
      "wrong_claim": "FMCW식은 펄스식과 동일하게 송수신 시각만 직접 측정한다.",
      "correct_rule": "FMCW식은 주파수 스윕과 지연된 수신파의 비트주파수를 이용한다.",
      "severity": "fatal",
      "affected_layers": [
        "B",
        "C"
      ],
      "message": "오류: FMCW식은 펄스식과 동일하게 송수신 시각만 직접 측정한다. 정정: FMCW식은 주파수 스윕과 지연된 수신파의 비트주파수를 이용한다.",
      "description": "오류: FMCW식은 펄스식과 동일하게 송수신 시각만 직접 측정한다. 정정: FMCW식은 주파수 스윕과 지연된 수신파의 비트주파수를 이용한다.",
      "grading_notes": "오류: FMCW식은 펄스식과 동일하게 송수신 시각만 직접 측정한다. 정정: FMCW식은 주파수 스윕과 지연된 수신파의 비트주파수를 이용한다."
    },
    {
      "id": "radar_fatal_beat_frequency_independent_of_slope",
      "claim": "FMCW 거리는 스윕 기울기와 무관하고 비트주파수만 알면 항상 동일하게 계산된다.",
      "correction": "D=cf_b/(2S)이므로 비트주파수와 스윕 기울기를 함께 사용한다.",
      "wrong_claim": "FMCW 거리는 스윕 기울기와 무관하고 비트주파수만 알면 항상 동일하게 계산된다.",
      "correct_rule": "D=cf_b/(2S)이므로 비트주파수와 스윕 기울기를 함께 사용한다.",
      "severity": "fatal",
      "affected_layers": [
        "B",
        "C"
      ],
      "message": "오류: FMCW 거리는 스윕 기울기와 무관하고 비트주파수만 알면 항상 동일하게 계산된다. 정정: D=cf_b/(2S)이므로 비트주파수와 스윕 기울기를 함께 사용한다.",
      "description": "오류: FMCW 거리는 스윕 기울기와 무관하고 비트주파수만 알면 항상 동일하게 계산된다. 정정: D=cf_b/(2S)이므로 비트주파수와 스윕 기울기를 함께 사용한다.",
      "grading_notes": "오류: FMCW 거리는 스윕 기울기와 무관하고 비트주파수만 알면 항상 동일하게 계산된다. 정정: D=cf_b/(2S)이므로 비트주파수와 스윕 기울기를 함께 사용한다."
    },
    {
      "id": "radar_fatal_narrow_band_better_resolution",
      "claim": "FMCW 변조 대역폭이 작을수록 거리 분해능이 좋아진다.",
      "correction": "대표식 ΔR≈c/(2B)에서 대역폭이 클수록 거리 분해능이 좋아진다.",
      "wrong_claim": "FMCW 변조 대역폭이 작을수록 거리 분해능이 좋아진다.",
      "correct_rule": "대표식 ΔR≈c/(2B)에서 대역폭이 클수록 거리 분해능이 좋아진다.",
      "severity": "fatal",
      "affected_layers": [
        "B",
        "C"
      ],
      "message": "오류: FMCW 변조 대역폭이 작을수록 거리 분해능이 좋아진다. 정정: 대표식 ΔR≈c/(2B)에서 대역폭이 클수록 거리 분해능이 좋아진다.",
      "description": "오류: FMCW 변조 대역폭이 작을수록 거리 분해능이 좋아진다. 정정: 대표식 ΔR≈c/(2B)에서 대역폭이 클수록 거리 분해능이 좋아진다.",
      "grading_notes": "오류: FMCW 변조 대역폭이 작을수록 거리 분해능이 좋아진다. 정정: 대표식 ΔR≈c/(2B)에서 대역폭이 클수록 거리 분해능이 좋아진다."
    },
    {
      "id": "radar_fatal_dielectric_no_effect",
      "claim": "측정물의 상대유전율은 반사에코에 전혀 영향을 주지 않는다.",
      "correction": "상대유전율은 반사계수와 에코마진에 영향을 준다.",
      "wrong_claim": "측정물의 상대유전율은 반사에코에 전혀 영향을 주지 않는다.",
      "correct_rule": "상대유전율은 반사계수와 에코마진에 영향을 준다.",
      "severity": "fatal",
      "affected_layers": [
        "B",
        "C"
      ],
      "message": "오류: 측정물의 상대유전율은 반사에코에 전혀 영향을 주지 않는다. 정정: 상대유전율은 반사계수와 에코마진에 영향을 준다.",
      "description": "오류: 측정물의 상대유전율은 반사에코에 전혀 영향을 주지 않는다. 정정: 상대유전율은 반사계수와 에코마진에 영향을 준다.",
      "grading_notes": "오류: 측정물의 상대유전율은 반사에코에 전혀 영향을 주지 않는다. 정정: 상대유전율은 반사계수와 에코마진에 영향을 준다."
    },
    {
      "id": "radar_fatal_echo_amplitude_is_level",
      "claim": "에코 진폭 자체가 거리 또는 레벨이다.",
      "correction": "거리는 왕복시간 또는 비트주파수로 구하고 진폭은 에코 신뢰도를 판단하는 정보이다.",
      "wrong_claim": "에코 진폭 자체가 거리 또는 레벨이다.",
      "correct_rule": "거리는 왕복시간 또는 비트주파수로 구하고 진폭은 에코 신뢰도를 판단하는 정보이다.",
      "severity": "fatal",
      "affected_layers": [
        "B",
        "C"
      ],
      "message": "오류: 에코 진폭 자체가 거리 또는 레벨이다. 정정: 거리는 왕복시간 또는 비트주파수로 구하고 진폭은 에코 신뢰도를 판단하는 정보이다.",
      "description": "오류: 에코 진폭 자체가 거리 또는 레벨이다. 정정: 거리는 왕복시간 또는 비트주파수로 구하고 진폭은 에코 신뢰도를 판단하는 정보이다.",
      "grading_notes": "오류: 에코 진폭 자체가 거리 또는 레벨이다. 정정: 거리는 왕복시간 또는 비트주파수로 구하고 진폭은 에코 신뢰도를 판단하는 정보이다."
    },
    {
      "id": "radar_fatal_zero_blocking_distance",
      "claim": "모든 레이더식 레벨계는 안테나 바로 앞까지 오차 없이 측정한다.",
      "correction": "송신 누설, 수신기 포화와 내부반사로 블로킹 거리가 발생할 수 있다.",
      "wrong_claim": "모든 레이더식 레벨계는 안테나 바로 앞까지 오차 없이 측정한다.",
      "correct_rule": "송신 누설, 수신기 포화와 내부반사로 블로킹 거리가 발생할 수 있다.",
      "severity": "fatal",
      "affected_layers": [
        "B",
        "C"
      ],
      "message": "오류: 모든 레이더식 레벨계는 안테나 바로 앞까지 오차 없이 측정한다. 정정: 송신 누설, 수신기 포화와 내부반사로 블로킹 거리가 발생할 수 있다.",
      "description": "오류: 모든 레이더식 레벨계는 안테나 바로 앞까지 오차 없이 측정한다. 정정: 송신 누설, 수신기 포화와 내부반사로 블로킹 거리가 발생할 수 있다.",
      "grading_notes": "오류: 모든 레이더식 레벨계는 안테나 바로 앞까지 오차 없이 측정한다. 정정: 송신 누설, 수신기 포화와 내부반사로 블로킹 거리가 발생할 수 있다."
    },
    {
      "id": "radar_fatal_process_conditions_never_matter",
      "claim": "증기, 고압, 응축, 거품, 난류와 안테나 오염은 레이더 측정에 절대로 영향을 주지 않는다.",
      "correction": "영향이 상대적으로 작을 수 있으나 공정조건과 설치조건에 따라 에코품질과 신뢰도가 달라진다.",
      "wrong_claim": "증기, 고압, 응축, 거품, 난류와 안테나 오염은 레이더 측정에 절대로 영향을 주지 않는다.",
      "correct_rule": "영향이 상대적으로 작을 수 있으나 공정조건과 설치조건에 따라 에코품질과 신뢰도가 달라진다.",
      "severity": "fatal",
      "affected_layers": [
        "B",
        "C"
      ],
      "message": "오류: 증기, 고압, 응축, 거품, 난류와 안테나 오염은 레이더 측정에 절대로 영향을 주지 않는다. 정정: 영향이 상대적으로 작을 수 있으나 공정조건과 설치조건에 따라 에코품질과 신뢰도가 달라진다.",
      "description": "오류: 증기, 고압, 응축, 거품, 난류와 안테나 오염은 레이더 측정에 절대로 영향을 주지 않는다. 정정: 영향이 상대적으로 작을 수 있으나 공정조건과 설치조건에 따라 에코품질과 신뢰도가 달라진다.",
      "grading_notes": "오류: 증기, 고압, 응축, 거품, 난류와 안테나 오염은 레이더 측정에 절대로 영향을 주지 않는다. 정정: 영향이 상대적으로 작을 수 있으나 공정조건과 설치조건에 따라 에코품질과 신뢰도가 달라진다."
    },
    {
      "id": "radar_fatal_no_false_echo_installation_error",
      "claim": "레이더식은 노즐, 벽, 교반기와 설치각도에 관계없이 항상 실제 표면만 검출한다.",
      "correction": "내부구조물과 부적절한 설치는 허위에코와 다중반사를 만들 수 있다.",
      "wrong_claim": "레이더식은 노즐, 벽, 교반기와 설치각도에 관계없이 항상 실제 표면만 검출한다.",
      "correct_rule": "내부구조물과 부적절한 설치는 허위에코와 다중반사를 만들 수 있다.",
      "severity": "fatal",
      "affected_layers": [
        "B",
        "C"
      ],
      "message": "오류: 레이더식은 노즐, 벽, 교반기와 설치각도에 관계없이 항상 실제 표면만 검출한다. 정정: 내부구조물과 부적절한 설치는 허위에코와 다중반사를 만들 수 있다.",
      "description": "오류: 레이더식은 노즐, 벽, 교반기와 설치각도에 관계없이 항상 실제 표면만 검출한다. 정정: 내부구조물과 부적절한 설치는 허위에코와 다중반사를 만들 수 있다.",
      "grading_notes": "오류: 레이더식은 노즐, 벽, 교반기와 설치각도에 관계없이 항상 실제 표면만 검출한다. 정정: 내부구조물과 부적절한 설치는 허위에코와 다중반사를 만들 수 있다."
    }
  ],
  "safe_expressions": [
    "레이더식 레벨계는 송신·주파수생성부, 안테나, 수신·혼합부, 거리신호처리부, 레벨환산부 및 출력부로 구성되며 펄스식과 FMCW식 모두 표면 반사에코를 이용한다.",
    "안테나는 마이크로파 전자기파를 방사하고 액면 또는 분체표면에서 반사된 에코를 수신하며 레이더식 레벨계는 음파가 아니라 전자기파를 사용한다.",
    "펄스식 레이더는 송신펄스와 반사펄스 사이의 왕복 비행시간 τ를 측정하며 수신지연은 안테나와 표면 사이 왕복경로에 해당한다.",
    "펄스식 자유공간 레이더에서 기준점부터 표면까지의 편도거리는 D=v_g·τ/2로 계산한다. v_g는 실제 전파경로인 기체공간의 전파속도이며 일반 공기에서는 c_0에 가깝다. 고압가스나 고밀도 증기에서는 전파속도 보정 가능성을 검토한다.",
    "FMCW 레이더는 시간에 따라 주파수가 선형적으로 변하는 처프를 연속 송신하며 스윕 기울기는 S=Δf/T_s로 정의할 수 있다.",
    "정지표면과 이상적인 선형 처프에서 스윕 기울기 S=B/T_s, 비트주파수 f_b=Sτ이며 거리는 D=v_g·f_b/(2S)=v_g·f_b·T_s/(2B)이다. 실제 계기는 스윕 비선형, 신호처리와 기체공간 전파속도 영향을 함께 고려한다.",
    "FMCW의 이상적 거리 분해능은 ΔR≈v_g/(2B)이다. 이는 두 인접 반사면을 분리하는 능력이며 단일 표면의 측정 정확도, 반복성 또는 FFT bin 간격과 동일하지 않다. 정확도는 S/N비, 주파수·위상 추정, 보간, 스윕 선형성, 교정과 설치조건의 영향을 함께 받는다.",
    "레이더가 측정한 기준점에서 표면까지의 거리 D와 빈 탱크 기준거리 E를 이용하여 레벨은 L=E-D로 계산하며 기준면과 탱크 기준점이 일치해야 한다.",
    "상대유전율은 경계면 반사계수와 에코강도에 영향을 주며 공기에서 비자성 유전체로 수직입사할 때 전기장 진폭 반사계수는 Γ=(1-√ε_r)/(1+√ε_r)이며, 그 크기는 |Γ|=(√ε_r-1)/(√ε_r+1)이다.",
    "저유전율 유체나 분체는 반사에코가 약할 수 있으므로 거리, 표면상태, 안테나 이득, 잡음 및 에코마진을 함께 검토해야 한다.",
    "안테나 빔각과 측정거리가 조사면적을 결정하며 빔 경로에 벽, 노즐 또는 내부구조물이 들어오면 허위에코 가능성이 증가한다.",
    "같은 안테나 개구에서 높은 반송주파수는 좁은 빔과 소형 안테나 구현에 유리할 수 있다. 다만 FMCW 거리 분해능은 반송주파수 자체가 아니라 유효 변조 대역폭과 신호처리에 의해 결정되며 최대거리, 응축, 부착물, 공정창 및 비용을 함께 고려해야 한다.",
    "송신 누설, 수신기 포화, 내부반사 및 근거리 신호처리 한계로 블로킹 거리 또는 최소 측정거리가 발생할 수 있으며 최대레벨이 이 구간에 들어가지 않도록 해야 한다.",
    "노즐, 탱크 벽, 교반기, 보강재 및 가열코일은 허위에코를 만들 수 있고 탱크 구조와 표면 사이의 다중반사는 잘못된 거리피크를 만들 수 있다.",
    "거품, 난류, 파동 및 경사진 분체표면은 에코의 방향·진폭·분포를 변화시키며 필터와 평균화는 응답속도와 안정성의 절충을 가진다.",
    "일반적인 증기와 온도변화의 영향은 초음파식보다 작을 수 있으나 고압가스, 고밀도 증기, 응축 및 특수 가스층의 영향까지 항상 0이라고 단정할 수 없다.",
    "긴 노즐, 작은 노즐직경, 안테나 매몰, 빔 경로 장애물 및 측정면을 향하지 않은 부적절한 정렬은 측정오차를 유발한다. 액체에서는 일반적으로 안테나 축을 액면에 수직으로 정렬하고, 분체에서는 경사진 표면을 향하도록 제조사 지침과 정렬장치에 따라 의도적으로 기울일 수 있다.",
    "안테나의 부착물, 코팅, 응축 및 결로는 송수신 손실과 허위에코를 증가시킬 수 있으므로 퍼지, 가열, 적절한 재질과 예방정비를 검토한다.",
    "시운전 시 기준거리, 실제 레벨, 에코곡선, 에코마진과 허위에코 맵을 확인하고 거리창, 임계값, 추적설정 및 진단정보를 공정조건에 맞게 조정한다.",
    "펄스식은 왕복시간을, FMCW식은 스윕 기울기와 비트주파수를 이용하며 방식 선정은 거리, 분해능, 유전율, 공정조건, 설치공간, 기존설비 연계 및 비용을 기준으로 한다."
  ],
  "revision_notes": [
    "펄스식 왕복시간과 D=cτ/2 계약을 추가했다.",
    "FMCW 선형 스윕·비트주파수·거리 분해능 계약을 추가했다.",
    "유전율, 허위에코, 설치오차 및 현장 진단 계약을 추가했다.",
    "반송주파수의 빔 특성과 유효 변조 대역폭의 거리 분해능 역할을 분리했다.",
    "액체의 수직 정렬과 분체의 의도적 표면방향 정렬 조건을 구분했다.",
    "레이더 마스터 내용을 기존 Topic Pack 내부에 통합했다.",
    "별도 Topic ID 또는 Topic Pack 디렉터리를 생성하지 않았다.",
    "Pulse·FMCW·Echo·Threshold·UNZ·GWR 계약을 같은 팩에서 확장했다.",
    "Fatal 직접 점수 영향 레이어를 B/C로 제한했다."
  ],
  "topic_label": "레이더식 레벨계",
  "core_facts": [
    "레이더식 레벨계는 송신·주파수생성부, 안테나, 수신·혼합부, 거리신호처리부, 레벨환산부 및 출력부로 구성되며 펄스식과 FMCW식 모두 표면 반사에코를 이용한다.",
    "안테나는 마이크로파 전자기파를 방사하고 액면 또는 분체표면에서 반사된 에코를 수신하며 레이더식 레벨계는 음파가 아니라 전자기파를 사용한다.",
    "펄스식 레이더는 송신펄스와 반사펄스 사이의 왕복 비행시간 τ를 측정하며 수신지연은 안테나와 표면 사이 왕복경로에 해당한다.",
    "펄스식 자유공간 레이더에서 기준점부터 표면까지의 편도거리는 D=v_g·τ/2로 계산한다. v_g는 실제 전파경로인 기체공간의 전파속도이며 일반 공기에서는 c_0에 가깝다. 고압가스나 고밀도 증기에서는 전파속도 보정 가능성을 검토한다.",
    "FMCW 레이더는 시간에 따라 주파수가 선형적으로 변하는 처프를 연속 송신하며 스윕 기울기는 S=Δf/T_s로 정의할 수 있다.",
    "정지표면과 이상적인 선형 처프에서 스윕 기울기 S=B/T_s, 비트주파수 f_b=Sτ이며 거리는 D=v_g·f_b/(2S)=v_g·f_b·T_s/(2B)이다. 실제 계기는 스윕 비선형, 신호처리와 기체공간 전파속도 영향을 함께 고려한다.",
    "FMCW의 이상적 거리 분해능은 ΔR≈v_g/(2B)이다. 이는 두 인접 반사면을 분리하는 능력이며 단일 표면의 측정 정확도, 반복성 또는 FFT bin 간격과 동일하지 않다. 정확도는 S/N비, 주파수·위상 추정, 보간, 스윕 선형성, 교정과 설치조건의 영향을 함께 받는다.",
    "레이더가 측정한 기준점에서 표면까지의 거리 D와 빈 탱크 기준거리 E를 이용하여 레벨은 L=E-D로 계산하며 기준면과 탱크 기준점이 일치해야 한다.",
    "상대유전율은 경계면 반사계수와 에코강도에 영향을 주며 공기에서 비자성 유전체로 수직입사할 때 전기장 진폭 반사계수는 Γ=(1-√ε_r)/(1+√ε_r)이며, 그 크기는 |Γ|=(√ε_r-1)/(√ε_r+1)이다.",
    "저유전율 유체나 분체는 반사에코가 약할 수 있으므로 거리, 표면상태, 안테나 이득, 잡음 및 에코마진을 함께 검토해야 한다.",
    "안테나 빔각과 측정거리가 조사면적을 결정하며 빔 경로에 벽, 노즐 또는 내부구조물이 들어오면 허위에코 가능성이 증가한다.",
    "같은 안테나 개구에서 높은 반송주파수는 좁은 빔과 소형 안테나 구현에 유리할 수 있다. 다만 FMCW 거리 분해능은 반송주파수 자체가 아니라 유효 변조 대역폭과 신호처리에 의해 결정되며 최대거리, 응축, 부착물, 공정창 및 비용을 함께 고려해야 한다.",
    "송신 누설, 수신기 포화, 내부반사 및 근거리 신호처리 한계로 블로킹 거리 또는 최소 측정거리가 발생할 수 있으며 최대레벨이 이 구간에 들어가지 않도록 해야 한다.",
    "노즐, 탱크 벽, 교반기, 보강재 및 가열코일은 허위에코를 만들 수 있고 탱크 구조와 표면 사이의 다중반사는 잘못된 거리피크를 만들 수 있다.",
    "거품, 난류, 파동 및 경사진 분체표면은 에코의 방향·진폭·분포를 변화시키며 필터와 평균화는 응답속도와 안정성의 절충을 가진다.",
    "일반적인 증기와 온도변화의 영향은 초음파식보다 작을 수 있으나 고압가스, 고밀도 증기, 응축 및 특수 가스층의 영향까지 항상 0이라고 단정할 수 없다.",
    "긴 노즐, 작은 노즐직경, 안테나 매몰, 빔 경로 장애물 및 측정면을 향하지 않은 부적절한 정렬은 측정오차를 유발한다. 액체에서는 일반적으로 안테나 축을 액면에 수직으로 정렬하고, 분체에서는 경사진 표면을 향하도록 제조사 지침과 정렬장치에 따라 의도적으로 기울일 수 있다.",
    "안테나의 부착물, 코팅, 응축 및 결로는 송수신 손실과 허위에코를 증가시킬 수 있으므로 퍼지, 가열, 적절한 재질과 예방정비를 검토한다.",
    "시운전 시 기준거리, 실제 레벨, 에코곡선, 에코마진과 허위에코 맵을 확인하고 거리창, 임계값, 추적설정 및 진단정보를 공정조건에 맞게 조정한다.",
    "펄스식은 왕복시간을, FMCW식은 스윕 기울기와 비트주파수를 이용하며 방식 선정은 거리, 분해능, 유전율, 공정조건, 설치공간, 기존설비 연계 및 비용을 기준으로 한다."
  ]
}
